_SurfaceTopography.cpython-313-x86_64-linux-gnu.so
.surfacetopography.mesonpy.libs/pkgconfig/eigen3.pc
surfacetopography-1.21.1.data/data/SurfaceTopography/ChangeLog.md
surfacetopography-1.21.1.data/headers/eigen3/signature_of_eigen3_matrix_library
surfacetopography-1.21.1.data/headers/eigen3/Eigen/Cholesky
surfacetopography-1.21.1.data/headers/eigen3/Eigen/CholmodSupport
surfacetopography-1.21.1.data/headers/eigen3/Eigen/Core
surfacetopography-1.21.1.data/headers/eigen3/Eigen/Dense
surfacetopography-1.21.1.data/headers/eigen3/Eigen/Eigen
surfacetopography-1.21.1.data/headers/eigen3/Eigen/Eigenvalues
surfacetopography-1.21.1.data/headers/eigen3/Eigen/Geometry
surfacetopography-1.21.1.data/headers/eigen3/Eigen/Householder
surfacetopography-1.21.1.data/headers/eigen3/Eigen/IterativeLinearSolvers
surfacetopography-1.21.1.data/headers/eigen3/Eigen/Jacobi
surfacetopography-1.21.1.data/headers/eigen3/Eigen/KLUSupport
surfacetopography-1.21.1.data/headers/eigen3/Eigen/LU
surfacetopography-1.21.1.data/headers/eigen3/Eigen/MetisSupport
surfacetopography-1.21.1.data/headers/eigen3/Eigen/OrderingMethods
surfacetopography-1.21.1.data/headers/eigen3/Eigen/PaStiXSupport
surfacetopography-1.21.1.data/headers/eigen3/Eigen/PardisoSupport
surfacetopography-1.21.1.data/headers/eigen3/Eigen/QR
surfacetopography-1.21.1.data/headers/eigen3/Eigen/QtAlignedMalloc
surfacetopography-1.21.1.data/headers/eigen3/Eigen/SPQRSupport
surfacetopography-1.21.1.data/headers/eigen3/Eigen/SVD
surfacetopography-1.21.1.data/headers/eigen3/Eigen/Sparse
surfacetopography-1.21.1.data/headers/eigen3/Eigen/SparseCholesky
surfacetopography-1.21.1.data/headers/eigen3/Eigen/SparseCore
surfacetopography-1.21.1.data/headers/eigen3/Eigen/SparseLU
surfacetopography-1.21.1.data/headers/eigen3/Eigen/SparseQR
surfacetopography-1.21.1.data/headers/eigen3/Eigen/StdDeque
surfacetopography-1.21.1.data/headers/eigen3/Eigen/StdList
surfacetopography-1.21.1.data/headers/eigen3/Eigen/StdVector
surfacetopography-1.21.1.dist-info/LICENSE.md
surfacetopography-1.21.1.dist-info/METADATA
surfacetopography-1.21.1.dist-info/WHEEL
surfacetopography-1.21.1.dist-info/entry_points.txt
surfacetopography-1.21.1.dist-info/RECORD
