Metadata-Version: 2.1
Name: SurfaceTopography
Version: 1.21.1
Summary: Read and analyze surface topographies
Keywords: surface,topography,roughness,profilometry,profilometer,metrology,surface-metrology,AFM,SPM,confocal,interferometer,stylus,contact-mechanics,tribology,Alicona,Bruker,Dektak,Wyko,Veeco,Digital-Instruments,Keyence,Zygo,MetroPro,Sensofar,Olympus,LEXT,Park-Systems,JPK,NanoSurf,Mitutoyo,SurfTest,Agilent,Molecular-Imaging,MicroProf,FRT,X3P,ISO-5436,SUR,OPD,OPDx,VK4,VK6,AL3D,GWY,Gwyddion,WSxM,NetCDF,HDF5,IBW,Igor,height-map,surface-profile,line-scan,SRTM
Author-Email: Lars Pastewka <lars.pastewka@imtek.uni-freiburg.de>, Kai Haase <k.o.haase@googlemail.com>, =?utf-8?q?Johannes_H=C3=B6rmann?= <johannes.hoermann@imtek.uni-freiburg.de>, Till Junge <till.junge@altermail.ch>, =?utf-8?q?Michael_R=C3=B6ttger?= <info@michael-roettger.de>, Antoine Sanner <antoine.sanner@imtek.uni-freiburg.de>
License: ### MIT license
Classifier: Development Status :: 5 - Production/Stable
Classifier: Programming Language :: Python
Project-URL: documentation, https://contactengineering.github.io/SurfaceTopography/
Project-URL: repository, https://github.com/ContactEngineering/SurfaceTopography
Project-URL: changelog, https://github.com/ContactEngineering/SurfaceTopography/blob/master/SurfaceTopography/ChangeLog.md
Requires-Python: >=3.10.0
Requires-Dist: numpy>=2.0.0
Requires-Dist: scipy>=1.9.0
Requires-Dist: defusedxml
Requires-Dist: h5py
Requires-Dist: igor2
Requires-Dist: matplotlib>=1.0.0
Requires-Dist: muGrid>=0.103.0
Requires-Dist: NuMPI>=0.9.0
Requires-Dist: numpyencoder
Requires-Dist: openpyxl
Requires-Dist: Pillow
Requires-Dist: python-dateutil
Requires-Dist: pyyaml
Requires-Dist: requests
Requires-Dist: tiffile
Requires-Dist: xmltodict
Requires-Dist: olefile
Requires-Dist: pandas
Requires-Dist: pydantic
Requires-Dist: zstandard
Provides-Extra: test
Requires-Dist: flake8<8; extra == "test"
Requires-Dist: pytest; extra == "test"
Requires-Dist: pytest-cov; extra == "test"
Requires-Dist: pytest-flake8; extra == "test"
Requires-Dist: runtests; extra == "test"
